AI4SS
tests
