Metadata-Version: 1.0
Name: AI4SS
Version: 0.0.1
Summary: It is an active learning support vector machine library to classify school shooting
Home-page: UNKNOWN
Author: Minxing Zhang
Author-email: minxing.zhang@emory.edu
License: MIT
Platform: UNKNOWN
